{
    "edges": [
        {
            "data": {
                "source": "0",
                "relation": "学生",
                "target": "1",
                "type": "connection",
                "id": "c38e79d4-0433-4e87-826c-300b4cadc544"
            }
        },
        {
            "data": {
                "source": "0",
                "relation": "学生",
                "target": "2",
                "type": "connection",
                "id": "cbad3d56-cee7-4006-8a28-56e1acf0f0a0"
            }
        },
        {
            "data": {
                "source": "0",
                "relation": "学生",
                "target": "3",
                "type": "connection",
                "id": "00618917-dc95-4e56-93c7-5c88d9f5ccc8"
            }
        },
        {
            "data": {
                "source": "1",
                "relation": "作",
                "target": "4",
                "type": "connection",
                "id": "32ec3142-28f9-4a08-93b0-bb3052d99204"
            }
        },
        {
            "data": {
                "source": "2",
                "relation": "作",
                "target": "5",
                "type": "connection",
                "id": "9c8740f0-6c1d-4dad-81ef-33ab20d7195d"
            }
        },
        {
            "data": {
                "source": "3",
                "relation": "作",
                "target": "6",
                "type": "default",
                "id": "4d1df6ec-e0e9-413b-9893-79464e6ebb3e"
            }
        },
        {
            "data": {
                "source": "0",
                "relation": "成",
                "target": "7",
                "type": "default",
                "id": "4f30645e-951d-467e-835d-65b26bf3ca59"
            }
        },
        {
            "data": {
                "source": "0",
                "relation": "收编",
                "target": "8",
                "type": "default",
                "id": "2a689872-130a-492e-8474-1b27f5104635"
            }
        },
        {
            "data": {
                "source": "9",
                "relation": "成员",
                "target": "0",
                "type": "default",
                "id": "a32f0a16-10fa-4797-9c2a-eaf7b711b63d"
            }
        },
        {
            "data": {
                "source": "9",
                "relation": "成员",
                "target": "1",
                "type": "default",
                "id": "522539f9-d864-4d32-9e2b-60c85bbb17f6"
            }
        },
        {
            "data": {
                "source": "9",
                "relation": "成员",
                "target": "2",
                "type": "default",
                "id": "b02f7cfe-662a-490a-9644-57bd4410be75"
            }
        },
        {
            "data": {
                "source": "9",
                "relation": "成员",
                "target": "3",
                "type": "default",
                "id": "9b0eddba-826f-4b52-b821-0be283760d5d"
            }
        },
        {
            "data": {
                "source": "9",
                "relation": "成员",
                "target": "10",
                "type": "default",
                "id": "97d8e8db-0c1f-46fb-bc72-7863511b0981"
            }
        },
        {
            "data": {
                "source": "11",
                "relation": "包含",
                "target": "7",
                "type": "default",
                "id": "8db481a9-3541-4494-a1f1-6fa124a8de5c"
            }
        },
        {
            "data": {
                "source": "11",
                "relation": "包含",
                "target": "5",
                "type": "default",
                "id": "06217cdf-217b-47e9-b7d9-bbc63cd8d248"
            }
        },
        {
            "data": {
                "source": "11",
                "relation": "包含",
                "target": "6",
                "type": "default",
                "id": "2cf97cfe-3314-4f87-829d-159428c98f4e"
            }
        },
        {
            "data": {
                "source": "11",
                "relation": "包含",
                "target": "4",
                "type": "default",
                "id": "420d0717-6cca-4181-9d1d-3c92e9e3ed29"
            }
        },
        {
            "data": {
                "source": "0",
                "relation": "尊称",
                "target": "12",
                "type": "default",
                "id": "0543bdca-151f-4cc3-a64b-756c896c303e"
            }
        },
        {
            "data": {
                "source": "1",
                "relation": "尊称",
                "target": "13",
                "type": "default",
                "id": "63dab97f-6155-4f83-9264-e8bf5478b55b"
            }
        }
    ],
    "nodes": [
        {
            "data": {
                "name": "孔子哈哈哈哈哈哈",
                "id": "0",
                "type": "default",
                "property": [
                    "s"
                ]
            },
            "position": {
                "x": -234.5473002215894,
                "y": 51.11716290094573
            }
        },
        {
            "data": {
                "name": "孟子",
                "id": "1",
                "type": "default",
                "property": []
            },
            "position": {
                "x": -258.4375,
                "y": 338.4
            }
        },
        {
            "data": {
                "name": "曾子",
                "id": "2",
                "type": "default",
                "property": [
                    "s"
                ]
            },
            "position": {
                "x": 465.1875,
                "y": 338.4
            }
        },
        {
            "data": {
                "name": "子思",
                "id": "3",
                "type": "default",
                "property": []
            },
            "position": {
                "x": 827,
                "y": 338.4
            }
        },
        {
            "data": {
                "name": "《孟子》",
                "id": "4",
                "type": "thing",
                "property": [
                    "s"
                ]
            },
            "position": {
                "x": 206.75,
                "y": 535.8
            }
        },
        {
            "data": {
                "name": "《大学》",
                "id": "5",
                "type": "thing",
                "property": []
            },
            "position": {
                "x": 620.25,
                "y": 535.8
            }
        },
        {
            "data": {
                "name": "《中庸》",
                "id": "6",
                "type": "thing",
                "property": [
                    "s"
                ]
            },
            "position": {
                "x": 1033.75,
                "y": 535.8
            }
        },
        {
            "data": {
                "name": "《论语》",
                "id": "7",
                "type": "thing",
                "property": []
            },
            "position": {
                "x": 1188.8125,
                "y": 338.4
            }
        },
        {
            "data": {
                "name": "《诗经》",
                "id": "8",
                "type": "thing",
                "property": []
            },
            "position": {
                "x": 1550.625,
                "y": 338.4
            }
        },
        {
            "data": {
                "name": "儒家",
                "id": "9",
                "type": "thing",
                "property": []
            },
            "position": {
                "x": 1912.4375,
                "y": 338.4
            }
        },
        {
            "data": {
                "name": "董仲舒",
                "id": "10",
                "type": "individual",
                "property": [
                    "s"
                ]
            },
            "position": {
                "x": 1860.75,
                "y": 535.8
            }
        },
        {
            "data": {
                "name": "四书",
                "id": "11",
                "type": "individual",
                "property": []
            },
            "position": {
                "x": 1447.2500000000002,
                "y": 535.8
            }
        },
        {
            "data": {
                "name": "圣人",
                "id": "12",
                "type": "individual",
                "property": [
                    "s"
                ]
            },
            "position": {
                "x": 694.1540150564614,
                "y": -137.8979140526972
            }
        },
        {
            "data": {
                "name": "亚圣",
                "id": "13",
                "type": "individual",
                "property": []
            },
            "position": {
                "x": -206.75,
                "y": 535.8
            }
        }
    ]
}
